{
  "project_info": {
    "project_number": "955703170797",
    "project_id": "fir-test-b3781",
    "storage_bucket": "fir-test-b3781.appspot.com"
  },
  "client": [
    {
      "client_info": {
        "mobilesdk_app_id": "1:955703170797:android:54bf21086d88f56b295ee4",
        "android_client_info": {
          "package_name": "com.example.myapp"
        }
      },
      "oauth_client": [
        {
          "client_id": "955703170797-97bucdsjgkffcr2g69r67jkf2nc31ab9.apps.googleusercontent.com",
          "client_type": 3
        }
      ],
      "api_key": [
        {
          "current_key": "AIzaSyCCuJFxq9PzEtXimFxIAgv5x_1s3aPiuvI"
        }
      ],
      "services": {
        "appinvite_service": {
          "other_platform_oauth_client": [
            {
              "client_id": "955703170797-97bucdsjgkffcr2g69r67jkf2nc31ab9.apps.googleusercontent.com",
              "client_type": 3
            }
          ]
        }
      }
    }
  ],
  "configuration_version": "1"
}